thinkthinksyn/__init__.py
thinkthinksyn/client.py
thinkthinksyn/common_utils/concurrent_utils/__init__.py
thinkthinksyn/common_utils/concurrent_utils/async_helpers.py
thinkthinksyn/common_utils/concurrent_utils/file_lock.py
thinkthinksyn/common_utils/concurrent_utils/helper_funcs.py
thinkthinksyn/common_utils/concurrent_utils/nested_loop.py
thinkthinksyn/common_utils/concurrent_utils/shared_obj.py
thinkthinksyn/common_utils/data_structs/__init__.py
thinkthinksyn/common_utils/data_structs/advanced_builtins/__init__.py
thinkthinksyn/common_utils/data_structs/advanced_builtins/_utils.py
thinkthinksyn/common_utils/data_structs/advanced_builtins/dict.py
thinkthinksyn/common_utils/data_structs/advanced_builtins/queue.py
thinkthinksyn/common_utils/data_structs/advanced_builtins/set.py
thinkthinksyn/common_utils/data_structs/condition/__init__.py
thinkthinksyn/common_utils/data_structs/condition/_utils.py
thinkthinksyn/common_utils/data_structs/condition/condition.py
thinkthinksyn/common_utils/data_structs/condition/parser.py
thinkthinksyn/common_utils/data_structs/file_models/__init__.py
thinkthinksyn/common_utils/data_structs/file_models/_utils.py
thinkthinksyn/common_utils/data_structs/file_models/audio.py
thinkthinksyn/common_utils/data_structs/file_models/image.py
thinkthinksyn/common_utils/data_structs/file_models/loader.py
thinkthinksyn/common_utils/data_structs/file_models/pdf.py
thinkthinksyn/common_utils/data_structs/file_models/video.py
thinkthinksyn/common_utils/data_structs/geometry/__init__.py
thinkthinksyn/common_utils/data_structs/geometry/box2d.py
thinkthinksyn/common_utils/data_structs/geometry/line2d.py
thinkthinksyn/common_utils/data_structs/geometry/point2d.py
thinkthinksyn/common_utils/data_structs/geometry/polygon2d.py
thinkthinksyn/common_utils/data_structs/geometry/rect2d.py
thinkthinksyn/common_utils/data_structs/geometry/vec2d.py
thinkthinksyn/common_utils/decorators/__init__.py
thinkthinksyn/common_utils/decorators/cache.py
thinkthinksyn-0.0.2.dist-info/licenses/license
thinkthinksyn-0.0.2.dist-info/METADATA
thinkthinksyn-0.0.2.dist-info/WHEEL
thinkthinksyn-0.0.2.dist-info/top_level.txt
thinkthinksyn-0.0.2.dist-info/RECORD
